{"t39201":{"name":"高知市","paper":0,"sound":0,"url_city":"http://"},"t39202":{"name":"室戸市","paper":0,"sound":0,"url_city":"http://"},"t39203":{"name":"安芸市","paper":0,"sound":0,"url_city":"http://"},"t39204":{"name":"南国市","paper":0,"sound":0,"url_city":"http://"},"t39205":{"name":"土佐市","paper":0,"sound":0,"url_city":"http://"},"t39206":{"name":"須崎市","paper":0,"sound":0,"url_city":"http://"},"t39208":{"name":"宿毛市","paper":0,"sound":0,"url_city":"http://"},"t39209":{"name":"土佐清水市","paper":0,"sound":0,"url_city":"http://"},"t39210":{"name":"四万十市","paper":0,"sound":0,"url_city":"http://"},"t39211":{"name":"香南市","paper":0,"sound":0,"url_city":"http://"},"t39212":{"name":"香美市","paper":0,"sound":0,"url_city":"http://"},"t39301":{"name":"安芸郡東洋町","paper":0,"sound":0,"url_city":"http://"},"t39302":{"name":"安芸郡奈半利町","paper":0,"sound":0,"url_city":"http://"},"t39303":{"name":"安芸郡田野町","paper":0,"sound":0,"url_city":"http://"},"t39304":{"name":"安芸郡安田町","paper":0,"sound":0,"url_city":"http://"},"t39305":{"name":"安芸郡北川村","paper":0,"sound":0,"url_city":"http://"},"t39306":{"name":"安芸郡馬路村","paper":0,"sound":0,"url_city":"http://"},"t39307":{"name":"安芸郡芸西村","paper":0,"sound":0,"url_city":"http://"},"t39341":{"name":"長岡郡本山町","paper":0,"sound":0,"url_city":"http://"},"t39344":{"name":"長岡郡大豊町","paper":0,"sound":0,"url_city":"http://"},"t39363":{"name":"土佐郡土佐町","paper":0,"sound":0,"url_city":"http://"},"t39364":{"name":"土佐郡大川村","paper":0,"sound":0,"url_city":"http://"},"t39386":{"name":"吾川郡いの町","paper":0,"sound":0,"url_city":"http://"},"t39387":{"name":"吾川郡仁淀川町","paper":0,"sound":0,"url_city":"http://"},"t39401":{"name":"高岡郡中土佐町","paper":0,"sound":0,"url_city":"http://"},"t39402":{"name":"高岡郡佐川町","paper":0,"sound":0,"url_city":"http://"},"t39403":{"name":"高岡郡越知町","paper":0,"sound":0,"url_city":"http://"},"t39405":{"name":"高岡郡檮原町","paper":0,"sound":0,"url_city":"http://"},"t39410":{"name":"高岡郡日高村","paper":0,"sound":0,"url_city":"http://"},"t39411":{"name":"高岡郡津野町","paper":0,"sound":0,"url_city":"http://"},"t39412":{"name":"高岡郡四万十町","paper":0,"sound":0,"url_city":"http://"},"t39424":{"name":"幡多郡大月町","paper":0,"sound":0,"url_city":"http://"},"t39427":{"name":"幡多郡三原村","paper":0,"sound":0,"url_city":"http://"},"t39428":{"name":"幡多郡黒潮町","paper":0,"sound":0,"url_city":"http://"}}